pdfredact/__about__.py
pdfredact/__init__.py
pdfredact/utils.py
pdfredact-0.0.3.dist-info/METADATA
pdfredact-0.0.3.dist-info/WHEEL
pdfredact-0.0.3.dist-info/licenses/LICENSE.txt
pdfredact-0.0.3.dist-info/RECORD
